pabardb/__init__.py
pabardb/client.py
pabardb-0.1.4.dist-info/METADATA
pabardb-0.1.4.dist-info/WHEEL
pabardb-0.1.4.dist-info/top_level.txt
pabardb-0.1.4.dist-info/RECORD
