Metadata-Version: 2.4
Name: pabardb
Version: 0.1.4
Summary: PABAR DB Python SDK (embedded, local-first database engine)
Author-email: Barri / PABAR <noerbarry@gmail.com>
License: MIT
Project-URL: Homepage, https://github.com/noerbarry/pabardb
Project-URL: Source, https://github.com/noerbarry/pabardb
Project-URL: Issues, https://github.com/noerbarry/pabardb/issues
Keywords: database,embedded,local-first,pabar,edge
Classifier: Programming Language :: Python :: 3
Classifier: License :: OSI Approved :: MIT License
Classifier: Operating System :: OS Independent
Requires-Python: >=3.8
